namer/__init__.py
namer/__main__.py
namer/command.py
namer/comparison_results.py
namer/configuration.py
namer/configuration_utils.py
namer/database.py
namer/ffmpeg.py
namer/fileinfo.py
namer/http.py
namer/metadataapi.py
namer/models/__init__.py
namer/models/base.py
namer/models/file.py
namer/moviexml.py
namer/mutagen.py
namer/name_formatter.py
namer/namer.cfg.default
namer/namer.py
namer/tools/videohashes-amd64-linux
namer/tools/videohashes-amd64-macos
namer/tools/videohashes-amd64.exe
namer/tools/videohashes-arm-linux
namer/tools/videohashes-arm.exe
namer/tools/videohashes-arm64-linux
namer/tools/videohashes-arm64-macos
namer/tools/videohashes-arm64.exe
namer/videohashes.py
namer/videophash/__init__.py
namer/videophash/imagehash.py
namer/videophash/videophash.py
namer/videophash/videophashstash.py
namer/watchdog.py
namer/web/__init__.py
namer/web/actions.py
namer/web/public/android-chrome-192x192.png
namer/web/public/android-chrome-512x512.png
namer/web/public/apple-touch-icon.png
namer/web/public/assets/bundle.min.css
namer/web/public/assets/bundle.min.js
namer/web/public/assets/fonts/bootstrap-icons.woff
namer/web/public/assets/fonts/bootstrap-icons.woff2
namer/web/public/browserconfig.xml
namer/web/public/favicon-16x16.png
namer/web/public/favicon-32x32.png
namer/web/public/favicon.ico
namer/web/public/mstile-150x150.png
namer/web/public/safari-pinned-tab.svg
namer/web/public/site.webmanifest
namer/web/routes/__init__.py
namer/web/routes/api.py
namer/web/routes/web.py
namer/web/server.py
namer/web/templates/components/card.html
namer/web/templates/components/navigations.html
namer/web/templates/components/performersBadges.html
namer/web/templates/pages/failed.html
namer/web/templates/pages/index.html
namer/web/templates/pages/queue.html
namer/web/templates/pages/settings.html
namer/web/templates/partials/base.html
namer/web/templates/render/failedFiles.html
namer/web/templates/render/fileActions.html
namer/web/templates/render/logDetails.html
namer-1.19.16.dist-info/METADATA
namer-1.19.16.dist-info/WHEEL
namer-1.19.16.dist-info/entry_points.txt
namer-1.19.16.dist-info/RECORD
