Metadata-Version: 2.3
Name: namer
Version: 1.19.16
Summary: A namer of video files based on metadata from the porndb.
Author: 4c0d3r
Author-email: 4c0d3r@protonmail.com
Requires-Python: >=3.11,<3.15
Classifier: Programming Language :: Python :: 3
Classifier: Programming Language :: Python :: 3.11
Classifier: Programming Language :: Python :: 3.12
Classifier: Programming Language :: Python :: 3.13
Requires-Dist: ConfigUpdater (>=3.2,<4.0)
Requires-Dist: Flask-Compress (>=1.15,<2.0)
Requires-Dist: Pillow (>=11.1,<12.0)
Requires-Dist: Unidecode (>=1.3,<2.0)
Requires-Dist: ffmpeg-python (>=0.2,<0.3)
Requires-Dist: flask (>=3.1,<4.0)
Requires-Dist: jsonpickle (>=4.0,<5.0)
Requires-Dist: loguru (>=0.7,<0.8)
Requires-Dist: mutagen (>=1.47,<2.0)
Requires-Dist: numpy (>=2.1,<3.0)
Requires-Dist: orjson (>=3.10,<4.0)
Requires-Dist: oshash (>=0.1,<0.2)
Requires-Dist: pathvalidate (>=3.2,<4.0)
Requires-Dist: pony (>=0.7,<0.8)
Requires-Dist: rapidfuzz (>=3.9,<4.0)
Requires-Dist: requests (>=2.32,<3.0)
Requires-Dist: requests-cache (>=1.2,<2.0)
Requires-Dist: schedule (>=1.2,<2.0)
Requires-Dist: scipy (>=1.13,<2.0)
Requires-Dist: waitress (>=3.0,<4.0)
Requires-Dist: watchdog (>=6.0,<7.0)
